supercortex_flow/__init__.py
supercortex_flow-0.1.0.dist-info/METADATA
supercortex_flow-0.1.0.dist-info/WHEEL
supercortex_flow-0.1.0.dist-info/top_level.txt
supercortex_flow-0.1.0.dist-info/RECORD
