Metadata-Version: 2.4
Name: supercortex-flow
Version: 0.1.0
Requires-Python: >=3.8
Requires-Dist: requests>=2.31.0
Requires-Dist: websockets>=12.0
Requires-Dist: aiohttp>=3.8.0
Dynamic: requires-dist
Dynamic: requires-python
